README.txt
setup.py
Dangler.egg-info/PKG-INFO
Dangler.egg-info/SOURCES.txt
Dangler.egg-info/dependency_links.txt
Dangler.egg-info/entry_points.txt
Dangler.egg-info/requires.txt
Dangler.egg-info/top_level.txt
dangler/__init__.py
dangler/__main__.py
dangler/blocks.py
dangler/dangler.py