Metadata-Version: 1.0
Name: Dangler
Version: 0.3
Summary: A python script to convert html written with un-closed tags (like Hamlet templates) to html with closed tags.
Home-page: http://bitbucket.org/sras/dangler
Author: Sandeep.C.R
Author-email: sandeepcr2@gmail.com
License: MIT
Platform: UNKNOWN
